aiosmsactivate/__init__.py
aiosmsactivate/client.py
aiosmsactivate/exceptions.py
aiosmsactivate/models.py
aiosmsactivate/types.py
aiosmsactivate/utils.py
aiosmsactivate-1.5.1.dist-info/METADATA
aiosmsactivate-1.5.1.dist-info/WHEEL
aiosmsactivate-1.5.1.dist-info/licenses/LICENSE
aiosmsactivate-1.5.1.dist-info/RECORD
