Metadata-Version: 2.4
Name: aiosmsactivate
Version: 1.5.1
Summary: Python asyncio wrapper for sms-activate.io API
Project-URL: Homepage, https://github.com/AioSmsProviders/aiosmsactivate
Project-URL: Documentation, https://aiosmsproviders.github.io/aiosmsactivate/aiosmsactivate/client.html
Project-URL: Issues, https://github.com/AioSmsProviders/aiosmsactivate/issues
Author-email: lolkof <lolkofprog@gmail.com>, kewldan <kewldanil1@gmail.com>
License:                     GNU GENERAL PUBLIC LICENSE
License-File: LICENSE
Keywords: api,sms
Classifier: License :: OSI Approved :: MIT License
Classifier: Programming Language :: Python
Classifier: Programming Language :: Python :: 3
Requires-Python: >=3.10
Requires-Dist: aiohttp
Requires-Dist: async-lru
Requires-Dist: pydantic
